LICENSE
README.md
setup.cfg
setup.py
masked_ai/__init__.py
masked_ai/masker.py
masked_ai.egg-info/PKG-INFO
masked_ai.egg-info/SOURCES.txt
masked_ai.egg-info/dependency_links.txt
masked_ai.egg-info/requires.txt
masked_ai.egg-info/top_level.txt
masked_ai/core/__init__.py
masked_ai/core/masks.py
masked_ai/tests/__init__.py
masked_ai/tests/test_masker.py
masked_ai/tests/test_core/__init__.py
masked_ai/tests/test_core/test_masks.py