Metadata-Version: 2.1
Name: masked-ai
Version: 1.0.13
Summary: Masked AI
Home-page: https://github.com/cado-security/masked-ai
Download-URL: https://github.com/cado-security/masked-ai/archive/refs/heads/main.zip
Author: Cado Security
Author-email: maskedai@cadosecurity.com
License-File: LICENSE
